{
  "short_title": "מהו יחס",
  "subtitle": "משווים כמויות בנקודתיים: קוראים, מצמצמים, מרחיבים ומחלקים לפי יחס",
  "worksheet_note": "יחס משווה בין כמויות — והסדר שלו קובע! מרחיבים ומצמצמים בדיוק כמו שברים: כופלים או מחלקים את שני המספרים באותו מספר. ובחלוקה לפי יחס — קודם סכום החלקים, אחר כך גודל של חלק אחד, ורק אז כופלים. בדקו תמיד שהחלקים מסתכמים לכמות המקורית!",
  "worksheet": [
    {
      "title": "כותבים יחס",
      "tag": "easy",
      "body": "<p>כתבו את היחס המבוקש:</p><ol type=\"a\"><li>בקערה 3 כדורים אדומים ו-5 כחולים. היחס אדומים:כחולים ⟵ [[blank]]</li><li>במתכון: 2 כפות סוכר על כל 7 כוסות קמח. היחס סוכר:קמח ⟵ [[blank]]</li><li>בקבוצה 4 בנים ו-9 בנות. היחס בנות:בנים ⟵ [[blank]]</li><li>בקערה 6 תפוחים ו-6 תפוזים. היחס תפוחים:תפוזים בצורה מצומצמת ⟵ [[blank]]</li></ol>"
    },
    {
      "title": "קוראים בשני הכיוונים",
      "tag": "easy",
      "body": "<p>בחוג היחס בנים:בנות הוא [[eq:4:5]].</p><ol type=\"a\"><li>מה היחס בנות:בנים? ⟵ [[blank]]</li><li>אם בחוג בדיוק 4 בנים — כמה בנות יש? ⟵ [[blank]]</li><li>נכון או לא נכון: בחוג יש יותר בנות מבנים? ⟵ [[blank]]</li></ol>"
    },
    {
      "title": "מרחיבים",
      "tag": "easy",
      "body": "<p>השלימו את המספר החסר (▢):</p><ol type=\"a\"><li>[[eq:1:3 = 2:▢]] ⟵ [[blank]]</li><li>[[eq:1:3 = 5:▢]] ⟵ [[blank]]</li><li>[[eq:1:3 = ▢:30]] ⟵ [[blank]]</li><li>[[eq:2:5 = 4:▢]] ⟵ [[blank]]</li><li>[[eq:2:5 = ▢:20]] ⟵ [[blank]]</li></ol>"
    },
    {
      "title": "מצמצמים",
      "tag": "easy",
      "body": "<p>כתבו כל יחס בצורה המצומצמת ביותר:</p><ol type=\"a\"><li>[[eq:10:15]] ⟵ [[blank]]</li><li>[[eq:6:8]] ⟵ [[blank]]</li><li>[[eq:12:4]] ⟵ [[blank]]</li><li>[[eq:20:20]] ⟵ [[blank]]</li></ol>"
    },
    {
      "title": "חלק-לחלק וחלק-לשלם",
      "tag": "med",
      "body": "<p>בקבוצה 12 בנים ו-18 בנות.</p><ol type=\"a\"><li>מה היחס בנים:בנות בצורה מצומצמת?</li><li>מה היחס בנים:כל הקבוצה?</li><li>איזה חלק (שבר) מהקבוצה הם הבנים?</li></ol>",
      "lines": 3
    },
    {
      "title": "מיץ פטל",
      "tag": "med",
      "body": "<p>מכינים מיץ ביחס תרכיז:מים של [[eq:1:4]].</p><ol type=\"a\"><li>מזגו 3 כוסות תרכיז — כמה כוסות מים צריך? ⟵ [[blank]]</li><li>מזגו 20 כוסות מים — כמה כוסות תרכיז צריך? ⟵ [[blank]]</li><li>איזה חלק מהמשקה הוא תרכיז? ⟵ [[blank]]</li></ol>"
    },
    {
      "title": "אותו יחס?",
      "tag": "med",
      "body": "<p>קבעו לגבי כל זוג אם שני היחסים שווים, והסבירו בעזרת הרחבה או צמצום:</p><ol type=\"a\"><li>[[eq:2:3]] וגם [[eq:6:9]]</li><li>[[eq:4:6]] וגם [[eq:6:8]]</li><li>[[eq:5:10]] וגם [[eq:1:2]]</li><li>[[eq:3:4]] וגם [[eq:9:16]]</li></ol>",
      "lines": 4
    },
    {
      "title": "חלוקה לפי יחס — צעד אחר צעד",
      "tag": "med",
      "body": "<p>חלקו 40 ביחס [[eq:3:5]]:</p><ol type=\"a\"><li>סכום החלקים ⟵ [[blank]]</li><li>גודל של חלק אחד ⟵ [[blank]]</li><li>שני החלקים ⟵ [[blank]] וגם [[blank]]</li></ol><p>בדקו: האם שני החלקים מסתכמים ל-40?</p>"
    },
    {
      "title": "מחלקים כמויות",
      "tag": "med",
      "body": "<p>חלקו את הכמות לפי היחס:</p><ol type=\"a\"><li>24 ביחס [[eq:1:3]] ⟵ [[blank]]</li><li>35 ביחס [[eq:2:5]] ⟵ [[blank]]</li><li>54 ביחס [[eq:4:5]] ⟵ [[blank]]</li></ol>"
    },
    {
      "title": "הצבע הירוק המושלם",
      "tag": "med",
      "body": "<p>כדי לקבל ירוק מושלם מערבבים צהוב:כחול ביחס [[eq:2:3]].</p><ol type=\"a\"><li>יש לנו 8 כוסות צהוב — כמה כוסות כחול צריך?</li><li>רוצים להכין 30 כוסות צבע ירוק — כמה כוסות מכל צבע?</li></ol>",
      "lines": 3
    },
    {
      "title": "המתכון של סבתא",
      "tag": "med",
      "body": "<p>בעוגה של סבתא היחס קמח:סוכר הוא [[eq:3:1]].</p><ol type=\"a\"><li>לעוגה ענקית לוקחים 9 כוסות קמח — כמה כוסות סוכר צריך?</li><li>בפעם אחרת השתמשו יחד ב-12 כוסות של קמח וסוכר. כמה כוסות מכל אחד?</li></ol>",
      "lines": 3
    },
    {
      "title": "יחס של שלושה",
      "tag": "med",
      "body": "<p>בשרשרת 24 חרוזים בשלושה צבעים: אדום, כחול וירוק, ביחס [[eq:1:2:3]]. כמה חרוזים מכל צבע? (רמז: גם כאן מתחילים מסכום החלקים.)</p>",
      "lines": 2
    },
    {
      "title": "אתגר: כמה בסך הכול?",
      "tag": "hard",
      "body": "<p>בחוג היחס בנים:בנות הוא [[eq:3:4]], וידוע שיש בו 12 בנים. כמה בנות יש בחוג, וכמה ילדים בסך הכול?</p>",
      "lines": 2
    },
    {
      "title": "אתגר: ההפרש מספר",
      "tag": "hard",
      "body": "<p>היחס בין שתי כמויות הוא [[eq:5:3]], וההפרש ביניהן הוא 14. מהן שתי הכמויות? (רמז: כמה חלקים שווה ההפרש?)</p>",
      "lines": 3
    },
    {
      "title": "אתגר: מי מרוכז יותר?",
      "tag": "hard",
      "body": "<p>דנה מכינה מיץ ביחס תרכיז:מים של [[eq:2:5]], ויובל מכין מיץ ביחס תרכיז:מים של [[eq:3:7]]. המיץ של מי מרוכז (חזק) יותר? הסבירו בעזרת הרחבת היחסים לאותה כמות מים.</p>",
      "lines": 4
    },
    {
      "title": "אתגר: יחס שמשתנה",
      "tag": "hard",
      "body": "<p>בקבוצה היה היחס בנים:בנות [[eq:1:2]]. הצטרפו לקבוצה 4 בנים (ואף בת לא עזבה), ועכשיו היחס הוא [[eq:1:1]]. כמה ילדים היו בקבוצה בהתחלה?</p>",
      "lines": 3
    }
  ],
  "worksheet_answers": [
    "א. [[eq:3:5]] &nbsp; ב. [[eq:2:7]] &nbsp; ג. [[eq:9:4]] — הבנות ראשונות! &nbsp; ד. [[eq:6:6 = 1:1]]",
    "א. [[eq:5:4]] &nbsp; ב. 5 בנות &nbsp; ג. נכון — על כל 4 בנים יש 5 בנות",
    "א. 6 &nbsp; ב. 15 &nbsp; ג. 10 &nbsp; ד. 10 &nbsp; ה. 8",
    "א. [[eq:2:3]] &nbsp; ב. [[eq:3:4]] &nbsp; ג. [[eq:3:1]] &nbsp; ד. [[eq:1:1]]",
    "א. [[eq:12:18 = 2:3]] &nbsp; ב. בקבוצה 30 ילדים ⟵ [[eq:12:30 = 2:5]] &nbsp; ג. [[eq:[[12/30]] = [[2/5]]]] — שתי חמישיות",
    "א. [[eq:3 × 4 = 12]] כוסות מים &nbsp; ב. [[eq:20 ÷ 4 = 5]] כוסות תרכיז &nbsp; ג. חמישית ([[1/5]]) — כי בכל 5 כוסות משקה יש כוס תרכיז אחת",
    "א. שווים: הרחבה פי 3 &nbsp; ב. לא שווים: [[eq:4:6 = 2:3]] אבל [[eq:6:8 = 3:4]] &nbsp; ג. שווים: צמצום ב-5 &nbsp; ד. לא שווים: [[eq:3:4 = 12:16]] ולא [[eq:9:16]]",
    "א. [[eq:3 + 5 = 8]] &nbsp; ב. [[eq:40 ÷ 8 = 5]] &nbsp; ג. [[eq:3 × 5 = 15]] וגם [[eq:5 × 5 = 25]]. בדיקה: [[eq:15 + 25 = 40]] ✓",
    "א. כל חלק [[eq:24 ÷ 4 = 6]] ⟵ 6 ו-18 &nbsp; ב. כל חלק [[eq:35 ÷ 7 = 5]] ⟵ 10 ו-25 &nbsp; ג. כל חלק [[eq:54 ÷ 9 = 6]] ⟵ 24 ו-30",
    "א. 8 כוסות צהוב = 2 חלקים ⟵ כל חלק 4 ⟵ כחול: [[eq:3 × 4 = 12]] כוסות &nbsp; ב. סכום החלקים 5, כל חלק [[eq:30 ÷ 5 = 6]] ⟵ 12 צהוב ו-18 כחול",
    "א. [[eq:9 ÷ 3 = 3]] כוסות סוכר &nbsp; ב. סכום החלקים 4, כל חלק [[eq:12 ÷ 4 = 3]] ⟵ 9 כוסות קמח ו-3 כוסות סוכר",
    "סכום החלקים [[eq:1 + 2 + 3 = 6]], כל חלק [[eq:24 ÷ 6 = 4]] ⟵ 4 אדומים, 8 כחולים, 12 ירוקים. בדיקה: [[eq:4 + 8 + 12 = 24]] ✓",
    "12 בנים = 3 חלקים ⟵ כל חלק 4 ⟵ בנות: [[eq:4 × 4 = 16]], ובסך הכול [[eq:12 + 16 = 28]] ילדים",
    "ההפרש הוא [[eq:5 − 3 = 2]] חלקים ⟵ כל חלק [[eq:14 ÷ 2 = 7]] ⟵ הכמויות: [[eq:5 × 7 = 35]] וגם [[eq:3 × 7 = 21]]. בדיקה: [[eq:35 − 21 = 14]] ✓",
    "מרחיבים לאותה כמות מים (35): דנה [[eq:2:5 = 14:35]], יובל [[eq:3:7 = 15:35]]. על אותם מים ליובל יותר תרכיז (15 מול 14) ⟵ המיץ של יובל מרוכז יותר",
    "בנים = חלק אחד, בנות = 2 חלקים. אחרי ההצטרפות הבנים משתווים לבנות, כלומר 4 הבנים שהצטרפו הם בדיוק חלק אחד ⟵ כל חלק 4 ⟵ בהתחלה: 4 בנים ו-8 בנות, ובסך הכול 12 ילדים. בדיקה: [[eq:8:8 = 1:1]] ✓"
  ],
  "bank_sections": [
    {
      "title": "מדור א' — כותבים יחס ✏️",
      "icon": "✏️",
      "items": [
        "בקערה 3 תפוחים ו-7 תפוזים. מה היחס תפוחים:תפוזים?",
        "בקבוצה 12 בנים ו-14 בנות. מה היחס בנות:בנים בצורה מצומצמת?",
        "במתכון: 2 כוסות סוכר על כל 5 כוסות קמח. מה היחס סוכר:קמח?",
        "בחניון 6 מכוניות ו-6 אופנועים. מה היחס מכוניות:אופנועים בצורה מצומצמת?"
      ]
    },
    {
      "title": "מדור ב' — מרחיבים ומצמצמים 🔍",
      "icon": "🔍",
      "items": [
        "צמצמו את היחס 8:12.",
        "צמצמו את היחס 15:25.",
        "השלימו את המספר החסר: 3:4 = ?:12",
        "השלימו את המספר החסר: 2:7 = 10:?"
      ]
    },
    {
      "title": "מדור ג' — חלק וחלק, חלק ושלם 🧩",
      "icon": "🧩",
      "items": [
        "בקבוצה 8 בנים ו-12 בנות. מה היחס בנים:בנות בצורה מצומצמת?",
        "בקבוצה 8 בנים ו-12 בנות. מה היחס בנים:כל הקבוצה בצורה מצומצמת?",
        "בשקית 5 סוכריות אדומות ו-15 צהובות. איזה חלק מהסוכריות אדומות?",
        "היחס תרכיז:מים במשקה הוא 1:9. איזה חלק מהמשקה הוא תרכיז?"
      ]
    },
    {
      "title": "מדור ד' — מחלקים לפי יחס ⚖️",
      "icon": "⚖️",
      "items": [
        "חלקו 20 ביחס 1:4.",
        "חלקו 36 ביחס 4:5.",
        "חלקו 50 ביחס 2:3.",
        "חלקו 42 גולות בין שני ילדים ביחס 3:4. כמה גולות יקבל כל אחד?"
      ]
    },
    {
      "title": "מדור ה' — מהחיים 🧃",
      "icon": "🧃",
      "items": [
        "במתכון לפנקייק היחס קמח:חלב הוא 3:2. השתמשו ב-9 כוסות קמח — כמה כוסות חלב צריך?",
        "צבע כתום מכינים מאדום וצהוב ביחס 2:3. רוצים 25 כוסות צבע — כמה כוסות מכל צבע?",
        "בחוג היחס בנים:בנות הוא 4:5, ויש בו 12 בנים. כמה בנות יש?",
        "מיץ מכינים מתרכיז ומים ביחס 1:4. כמה כוסות מים צריך ל-6 כוסות תרכיז?"
      ]
    },
    {
      "title": "מדור ו' — אתגרים 🏆",
      "icon": "🏆",
      "items": [
        "היחס בין שתי כמויות הוא 7:3, וההפרש ביניהן 20. מהן שתי הכמויות?",
        "חלקו 60 לשלושה חלקים ביחס 1:2:3.",
        "בקבוצה היה היחס בנים:בנות 2:3. הצטרפו 5 בנים ועכשיו היחס 1:1. כמה ילדים בקבוצה עכשיו?"
      ]
    }
  ],
  "bank_answers": [
    "3:7",
    "14:12 ⟵ מצומצם: 7:6",
    "2:5",
    "6:6 = 1:1",
    "מחלקים ב-4: 2:3",
    "מחלקים ב-5: 3:5",
    "9 (כי הרחבנו פי 3: 9:12)",
    "35 (כי הרחבנו פי 5: 10:35)",
    "8:12 = 2:3",
    "בקבוצה 20 ילדים ⟵ 8:20 = 2:5",
    "רבע ([[eq:[[5/20]] = [[1/4]]]])",
    "עשירית — בכל 10 כוסות משקה יש כוס תרכיז אחת",
    "סכום החלקים 5, כל חלק 4 ⟵ 4 ו-16",
    "סכום החלקים 9, כל חלק 4 ⟵ 16 ו-20",
    "סכום החלקים 5, כל חלק 10 ⟵ 20 ו-30",
    "סכום החלקים 7, כל חלק 6 ⟵ 18 ו-24",
    "9 קמח = 3 חלקים ⟵ כל חלק 3 ⟵ [[eq:2 × 3 = 6]] כוסות חלב",
    "סכום החלקים 5, כל חלק 5 ⟵ 10 כוסות אדום ו-15 כוסות צהוב",
    "12 בנים = 4 חלקים ⟵ כל חלק 3 ⟵ [[eq:5 × 3 = 15]] בנות",
    "[[eq:6 × 4 = 24]] כוסות מים",
    "ההפרש 4 חלקים ⟵ כל חלק 5 ⟵ 35 ו-15",
    "סכום החלקים 6, כל חלק 10 ⟵ 10, 20, 30",
    "5 הבנים שהצטרפו = חלק אחד ⟵ כל חלק 5 ⟵ היו 10 בנים ו-15 בנות, ועכשיו [[eq:15 + 15 = 30]] ילדים"
  ],
  "extra_exercises": [
    {
      "title": "אותו יחס?",
      "difficulty": "medium",
      "description": "קבעו לגבי כל זוג אם שני היחסים שווים, והסבירו:\n\nא. $2:3$ ו-$6:9$\nב. $4:6$ ו-$6:8$\nג. $5:10$ ו-$1:2$\nד. $3:4$ ו-$9:16$",
      "solution": "א. שווים — הרחבה פי 3\nב. לא שווים — $4:6=2:3$ אבל $6:8=3:4$\nג. שווים — צמצום ב-5\nד. לא שווים — $3:4=12:16 \\ne 9:16$"
    },
    {
      "title": "הצבע הירוק המושלם",
      "difficulty": "medium",
      "description": "ירוק מושלם מקבלים מערבוב צהוב:כחול ביחס $2:3$.\n\nא. יש 8 כוסות צהוב — כמה כחול צריך?\nב. רוצים 30 כוסות צבע — כמה מכל צבע?",
      "solution": "א. 8 כוסות = 2 חלקים ⟵ חלק = 4 ⟵ כחול: $3 \\times 4 = 12$ כוסות\nב. סכום החלקים 5, כל חלק $30 \\div 5 = 6$ ⟵ 12 צהוב ו-18 כחול"
    },
    {
      "title": "המתכון של סבתא",
      "difficulty": "medium",
      "description": "בעוגה היחס קמח:סוכר הוא $3:1$.\n\nא. לקחו 9 כוסות קמח — כמה סוכר?\nב. השתמשו יחד ב-12 כוסות קמח וסוכר — כמה מכל אחד?",
      "solution": "א. $9 \\div 3 = 3$ כוסות סוכר\nב. סכום החלקים 4, כל חלק $12 \\div 4 = 3$ ⟵ 9 קמח ו-3 סוכר"
    },
    {
      "title": "יחס של שלושה",
      "difficulty": "medium",
      "description": "בשרשרת 24 חרוזים באדום, כחול וירוק ביחס $1:2:3$. כמה חרוזים מכל צבע?",
      "solution": "סכום החלקים $1+2+3=6$, כל חלק $24 \\div 6 = 4$ ⟵ 4 אדומים, 8 כחולים, 12 ירוקים\n\n**בדיקה:** $4+8+12=24$ ✓"
    },
    {
      "title": "מחלקים כמויות",
      "difficulty": "medium",
      "description": "חלקו לפי היחס:\n\nא. 24 ביחס $1:3$\nב. 35 ביחס $2:5$\nג. 54 ביחס $4:5$",
      "solution": "א. כל חלק $24 \\div 4 = 6$ ⟵ 6 ו-18\nב. כל חלק $35 \\div 7 = 5$ ⟵ 10 ו-25\nג. כל חלק $54 \\div 9 = 6$ ⟵ 24 ו-30"
    },
    {
      "title": "אתגר: כמה בסך הכול?",
      "difficulty": "hard",
      "description": "בחוג היחס בנים:בנות הוא $3:4$, ויש 12 בנים. כמה בנות יש, וכמה ילדים בסך הכול?",
      "solution": "12 בנים = 3 חלקים ⟵ כל חלק 4 ⟵ בנות: $4 \\times 4 = 16$, ובסך הכול $12+16=28$ ילדים"
    },
    {
      "title": "אתגר: ההפרש מספר",
      "difficulty": "hard",
      "description": "היחס בין שתי כמויות הוא $5:3$, וההפרש ביניהן 14. מהן הכמויות?",
      "solution": "ההפרש שווה $5-3=2$ חלקים ⟵ כל חלק $14 \\div 2 = 7$ ⟵ הכמויות $35$ ו-$21$\n\n**בדיקה:** $35-21=14$ ✓ וגם $35:21=5:3$ ✓"
    },
    {
      "title": "אתגר: מי מרוכז יותר?",
      "difficulty": "hard",
      "description": "דנה מכינה מיץ ביחס תרכיז:מים $2:5$, ויובל ביחס $3:7$. של מי מרוכז יותר?",
      "solution": "מרחיבים לאותה כמות מים (35): דנה $2:5=14:35$, יובל $3:7=15:35$.\n\nעל אותה כמות מים ליובל יותר תרכיז — המיץ של יובל מרוכז יותר."
    },
    {
      "title": "אתגר: יחס שמשתנה",
      "difficulty": "hard",
      "description": "בקבוצה היה היחס בנים:בנות $1:2$. הצטרפו 4 בנים, ועכשיו היחס $1:1$. כמה ילדים היו בהתחלה?",
      "solution": "בנים = חלק אחד, בנות = 2 חלקים. אחרי ההצטרפות הבנים השתוו לבנות, כלומר 4 הבנים הם בדיוק חלק אחד ⟵ כל חלק 4 ⟵ בהתחלה 4 בנים ו-8 בנות: $12$ ילדים\n\n**בדיקה:** עכשיו $8:8=1:1$ ✓"
    }
  ]
}
